{
  "plugin": {
    "totalDownloads": 250,
    "stargazers": 0,
    "createdAt": "2026-07-01T19:38:09Z",
    "latestReleaseAt": "2026-07-19T23:53:50Z",
    "lastCommitDate": "2026-07-19T23:51:02Z",
    "commitCountInLast24Months": 16,
    "totalReleases": 11,
    "releases": [
      {
        "publishedAt": "2026-07-01T19:38:40Z",
        "downloads": 26
      },
      {
        "publishedAt": "2026-07-01T19:46:37Z",
        "downloads": 31
      },
      {
        "publishedAt": "2026-07-03T17:59:15Z",
        "downloads": 26
      },
      {
        "publishedAt": "2026-07-05T14:28:09Z",
        "downloads": 7
      },
      {
        "publishedAt": "2026-07-05T15:22:58Z",
        "downloads": 7
      },
      {
        "publishedAt": "2026-07-05T18:18:07Z",
        "downloads": 5
      },
      {
        "publishedAt": "2026-07-05T18:39:54Z",
        "downloads": 5
      },
      {
        "publishedAt": "2026-07-05T18:51:56Z",
        "downloads": 14
      },
      {
        "publishedAt": "2026-07-06T18:41:14Z",
        "downloads": 11
      },
      {
        "publishedAt": "2026-07-07T20:54:05Z",
        "downloads": 90
      },
      {
        "publishedAt": "2026-07-19T23:53:50Z",
        "downloads": 28
      }
    ],
    "openIssues": [],
    "closedIssues": [],
    "openPRs": [],
    "closedPRs": [],
    "mergedPRs": []
  },
  "now": "2026-07-24T01:14:07.326Z"
}