{
  "plugin": {
    "totalDownloads": 12,
    "stargazers": 0,
    "createdAt": "2026-06-24T09:47:17Z",
    "latestReleaseAt": "2026-06-24T14:23:57Z",
    "lastCommitDate": "2026-06-24T14:23:37Z",
    "commitCountInLast24Months": 15,
    "totalReleases": 3,
    "releases": [
      {
        "publishedAt": "2026-06-24T09:47:40Z",
        "downloads": 2
      },
      {
        "publishedAt": "2026-06-24T14:20:04Z",
        "downloads": 1
      },
      {
        "publishedAt": "2026-06-24T14:23:57Z",
        "downloads": 9
      }
    ],
    "openIssues": [],
    "closedIssues": [],
    "openPRs": [],
    "closedPRs": [],
    "mergedPRs": []
  },
  "now": "2026-06-27T01:35:40.810Z"
}