{
  "plugin": {
    "totalDownloads": 43,
    "stargazers": 1,
    "createdAt": "2026-04-11T04:28:42Z",
    "latestReleaseAt": "2026-04-27T18:51:58Z",
    "lastCommitDate": "2026-04-27T18:51:33Z",
    "commitCountInLast24Months": 16,
    "totalReleases": 2,
    "releases": [
      {
        "publishedAt": "2026-04-23T20:31:41Z",
        "downloads": 2
      },
      {
        "publishedAt": "2026-04-27T18:51:58Z",
        "downloads": 41
      }
    ],
    "openIssues": [],
    "closedIssues": [],
    "openPRs": [],
    "closedPRs": [],
    "mergedPRs": []
  },
  "now": "2026-05-19T01:47:59.704Z"
}